<?xml version="1.0" encoding="utf-8" ?>
<dwsync>
<file name="admin-css-js-in.inc.php" server="142.4.17.153/public_html/" local="129718620000000000" remote="129718620000000000" />
<file name="admin-css-js.inc.php" server="142.4.17.153/public_html/" local="129718620000000000" remote="129718620000000000" />
<file name="admin-notices.inc.php" server="142.4.17.153/public_html/" local="129718620000000000" remote="129718620000000000" />
<file name="class.inc.php" server="142.4.17.153/public_html/" local="129718620000000000" remote="129718620000000000" />
<file name="index.php" server="142.4.17.153/public_html/" local="129718620000000000" remote="129718620000000000" />
<file name="installation.inc.php" server="142.4.17.153/public_html/" local="129718620000000000" remote="129718620000000000" />
<file name="menu-pages.inc.php" server="142.4.17.153/public_html/" local="129718620000000000" remote="129718620000000000" />
<file name="readmes.inc.php" server="142.4.17.153/public_html/" local="129718620000000000" remote="129718620000000000" />
<file name="utilities.inc.php" server="142.4.17.153/public_html/" local="129718620000000000" remote="129718620000000000" />
<file name="utils-arrays.inc.php" server="142.4.17.153/public_html/" local="129718620000000000" remote="129718620000000000" />
<file name="utils-conds.inc.php" server="142.4.17.153/public_html/" local="129718620000000000" remote="129718620000000000" />
<file name="utils-css.inc.php" server="142.4.17.153/public_html/" local="129718620000000000" remote="129718620000000000" />
<file name="utils-strings.inc.php" server="142.4.17.153/public_html/" local="129718620000000000" remote="129718620000000000" />
<file name="utils-urls.inc.php" server="142.4.17.153/public_html/" local="129718620000000000" remote="129718620000000000" />
<file name="widget.inc.php" server="142.4.17.153/public_html/" local="129718620000000000" remote="129718620000000000" />
</dwsync>